{
  "version": "2.2.0",
  "summary": {
    "title": "Modelo de amenazas - Biblioteca Universitaria",
    "owner": "Paloma Osiris Báez Lara",
    "description": "El sitio web de la biblioteca universitaria es la primera implementación de un sitio web para brindar servicios en línea a los bibliotecarios y usuarios de la biblioteca (estudiantes y personal universitario). Como esta es la primera implementación del sitio\nweb, la funcionalidad será limitada. Serán tres usuarios de la aplicación:\n1. Estudiantes\n2. Personal\n3. Bibliotecarios\nEl personal y los estudiantes podrán iniciar sesión y buscar libros, y los miembros del personal podrán solicitar libros. Los bibliotecarios podrán iniciar sesión, agregar libros, agregar usuarios y buscar libros.",
    "id": 0
  },
  "detail": {
    "contributors": [
      {
        "name": "Miriam Ramírez"
      }
    ],
    "diagrams": [
      {
        "id": 3,
        "title": "New STRIDE diagram",
        "diagramType": "STRIDE",
        "placeholder": "New STRIDE diagram description",
        "thumbnail": "./public/content/images/thumbnail.stride.jpg",
        "version": "2.2.0",
        "cells": [
          {
            "position": {
              "x": 340,
              "y": 110
            },
            "size": {
              "width": 112.5,
              "height": 60
            },
            "attrs": {
              "text": {
                "text": "Usuarios"
              },
              "body": {
                "stroke": "red",
                "strokeWidth": 2.5,
                "strokeDasharray": null
              }
            },
            "visible": true,
            "shape": "actor",
            "id": "32d404da-89de-4432-b650-cd7b55bea9be",
            "zIndex": 1,
            "data": {
              "type": "tm.Actor",
              "name": "Usuarios",
              "description": "(1) Usuario web anónimo.\n(2) Usuario con credenciales de\ninicio de sesión válidas.\n(3) Usuario con credenciales de\ninicio de sesión no válidas.",
              "outOfScope": false,
              "reasonOutOfScope": "",
              "hasOpenThreats": true,
              "providesAuthentication": false,
              "threats": [
                {
                  "id": "9cf39cac-7659-454c-bf4c-4619c7b260be",
                  "title": "Suplantación de identidad",
                  "status": "Open",
                  "severity": "Low",
                  "type": "Spoofing",
                  "description": "Acción de amenaza destinada\na acceder y utilizar las\ncredenciales de otro usuario,\ncomo el nombre de usuario y\nla contraseña.",
                  "mitigation": "1. Autenticación\nadecuada\n2. Proteger datos secretos\n3. No almacenar secretos",
                  "modelType": "STRIDE",
                  "new": false,
                  "number": 7,
                  "score": ""
                }
              ]
            }
          },
          {
            "position": {
              "x": 510,
              "y": 330
            },
            "size": {
              "width": 140,
              "height": 100
            },
            "attrs": {
              "text": {
                "text": "Sitio web\n biblioteca\n"
              },
              "body": {
                "stroke": "red",
                "strokeWidth": 2.5,
                "strokeDasharray": null
              }
            },
            "visible": true,
            "shape": "process",
            "id": "b40f6ef8-e1d8-4714-aa98-a0c87e70ba6b",
            "zIndex": 2,
            "data": {
              "type": "tm.Process",
              "name": "Sitio web\n biblioteca\n",
              "description": "El sitio web de la biblioteca\nuniversitaria se ejecutará en un\nservidor Linux con Apache. Este\nservidor será reforzado según el\nestándar de protección de servidores\nde la universidad.",
              "outOfScope": false,
              "reasonOutOfScope": "",
              "hasOpenThreats": true,
              "handlesCardPayment": false,
              "handlesGoodsOrServices": false,
              "isWebApplication": false,
              "privilegeLevel": "",
              "threats": [
                {
                  "id": "85f8b083-8a21-4779-8da1-7cdf2bfa5ac9",
                  "title": "Denegación de servicio",
                  "status": "Open",
                  "severity": "Medium",
                  "type": "Denial of service",
                  "description": "Un atacante podría denegar el\nacceso a usuarios válidos,\nhaciendo que el servidor web\nno esté disponible o sea\ninutilizable temporalmente\npor medio del envío de\nmúltiples peticiones\nsimultaneas.",
                  "mitigation": "Se utiliza un balanceo de\ncargas en el servidor web.\nSe monitorean las direcciones\nIP de los clientes y al encontrar\nun posible ataque, se bloquea\nel acceso.\nSe considera contratar un\nservicio de VPN para ocultar la\ndirección IP pública a los\nclientes.",
                  "modelType": "STRIDE",
                  "new": false,
                  "number": 1,
                  "score": ""
                }
              ]
            }
          },
          {
            "shape": "trust-boundary-curve",
            "width": 200,
            "height": 100,
            "zIndex": 10,
            "connector": "smooth",
            "data": {
              "type": "tm.Boundary",
              "name": "Usuario/Web\nserver límite",
              "description": "",
              "isTrustBoundary": true,
              "hasOpenThreats": false
            },
            "id": "bbef483e-0129-4657-9250-dd448becf2aa",
            "source": {
              "x": 290,
              "y": 140
            },
            "target": {
              "x": 830,
              "y": 140
            },
            "vertices": [
              {
                "x": 370,
                "y": 200
              },
              {
                "x": 580,
                "y": 180
              },
              {
                "x": 740,
                "y": 200
              }
            ],
            "labels": [
              "Usuario/Web\nserver límite"
            ]
          },
          {
            "shape": "flow",
            "attrs": {
              "line": {
                "stroke": "red",
                "strokeWidth": 2.5,
                "targetMarker": {
                  "name": "block"
                },
                "sourceMarker": {
                  "name": ""
                },
                "strokeDasharray": null
              }
            },
            "width": 200,
            "height": 100,
            "zIndex": 10,
            "connector": "smooth",
            "data": {
              "type": "tm.Flow",
              "name": "Web Response",
              "description": "Respuestas enviadas por la\naplicación hacia los bibliotecarios.",
              "outOfScope": false,
              "reasonOutOfScope": "",
              "hasOpenThreats": true,
              "isBidirectional": false,
              "isEncrypted": false,
              "isPublicNetwork": false,
              "protocol": "",
              "threats": [
                {
                  "id": "398fd857-92c2-4efb-884f-b992eaa3fe6f",
                  "title": "El flujo de datos debe utilizar HTTP/S",
                  "status": "Open",
                  "severity": "High",
                  "type": "Information disclosure",
                  "description": "Estas respuestas se transmiten\na traves de la Internet pública\ny podrían ser interceptadas\npor un atacante.",
                  "mitigation": "Las respuestas deberian\nrequerir HTTPS/S. Esto\nproporcionara\nconfidencialidad e\nintegridad. HTTP no debe\nser compatible.",
                  "modelType": "STRIDE",
                  "new": false,
                  "number": 4,
                  "score": ""
                }
              ]
            },
            "id": "6c9eb971-5c6c-4a1f-9d33-33831cda41ce",
            "source": {
              "cell": "b40f6ef8-e1d8-4714-aa98-a0c87e70ba6b"
            },
            "target": {
              "x": 710,
              "y": 170
            },
            "labels": [
              "Web Response"
            ],
            "vertices": [
              {
                "x": 660,
                "y": 260
              },
              {
                "x": 680,
                "y": 230
              }
            ]
          },
          {
            "shape": "flow",
            "attrs": {
              "line": {
                "stroke": "red",
                "strokeWidth": 2.5,
                "targetMarker": {
                  "name": "block"
                },
                "sourceMarker": {
                  "name": ""
                },
                "strokeDasharray": null
              }
            },
            "width": 200,
            "height": 100,
            "zIndex": 10,
            "connector": "smooth",
            "data": {
              "type": "tm.Flow",
              "name": "Web Request",
              "description": "Respuestas recibidas por la\naplicación hacia los bibliotecarios.",
              "outOfScope": false,
              "reasonOutOfScope": "",
              "hasOpenThreats": true,
              "isBidirectional": false,
              "isEncrypted": false,
              "isPublicNetwork": false,
              "protocol": "",
              "threats": [
                {
                  "id": "a57fc070-3136-4855-955f-1c8083b0047f",
                  "title": "El flujo de datos debe utilizar HTTP/S",
                  "status": "Open",
                  "severity": "High",
                  "type": "Information disclosure",
                  "description": "Estas solicitudes se\ntransmiten a través de la\nInternet pública y podrían ser\ninterceptadas por un atacante.",
                  "mitigation": "Las solicitudes deberían\nrequerir HTTPS/S. Esto\nproporcionara\nconfidencialidad e\nintegridad. HTTP no debe\nser compatible.",
                  "modelType": "STRIDE",
                  "new": false,
                  "number": 5,
                  "score": ""
                }
              ]
            },
            "id": "f32a0959-f9b7-4ae6-98a5-24892c81ad94",
            "source": {
              "x": 760,
              "y": 170
            },
            "target": {
              "cell": "b40f6ef8-e1d8-4714-aa98-a0c87e70ba6b"
            },
            "labels": [
              "Web Request"
            ],
            "vertices": [
              {
                "x": 770,
                "y": 300
              }
            ]
          },
          {
            "shape": "flow",
            "attrs": {
              "line": {
                "stroke": "red",
                "strokeWidth": 2.5,
                "targetMarker": {
                  "name": "block"
                },
                "sourceMarker": {
                  "name": ""
                },
                "strokeDasharray": null
              }
            },
            "width": 200,
            "height": 100,
            "zIndex": 10,
            "connector": "smooth",
            "data": {
              "type": "tm.Flow",
              "name": "Web Response\n",
              "description": "Respuestas enviadas por la\naplicación hacia los usuarios.",
              "outOfScope": false,
              "reasonOutOfScope": "",
              "hasOpenThreats": true,
              "isBidirectional": false,
              "isEncrypted": false,
              "isPublicNetwork": false,
              "protocol": "",
              "threats": [
                {
                  "id": "19e486e6-8278-4efb-b7d0-b9346da2a36f",
                  "title": "El flujo de datos debe utilizar HTTP/S",
                  "status": "Open",
                  "severity": "High",
                  "type": "Information disclosure",
                  "description": "Estas solicitudes se\ntransmiten a través\nde la Internet\npública y podrían ser\ninterceptadas por un\natacante.",
                  "mitigation": "Las solicitudes deberían\nrequerir HTTPS/S. Esto\nproporcionara confidencialidad\ne integridad. HTTP no debe ser\ncompatible.",
                  "modelType": "STRIDE",
                  "new": false,
                  "number": 3,
                  "score": ""
                }
              ]
            },
            "id": "054d1b0e-1a7f-48a2-897b-255a3bf76a88",
            "source": {
              "cell": "b40f6ef8-e1d8-4714-aa98-a0c87e70ba6b"
            },
            "target": {
              "cell": "32d404da-89de-4432-b650-cd7b55bea9be"
            },
            "vertices": [
              {
                "x": 480,
                "y": 330
              },
              {
                "x": 400,
                "y": 300
              },
              {
                "x": 370,
                "y": 250
              }
            ],
            "labels": [
              "Web Response\n"
            ]
          },
          {
            "shape": "flow",
            "attrs": {
              "line": {
                "stroke": "#333333",
                "targetMarker": {
                  "name": "block"
                },
                "sourceMarker": {
                  "name": ""
                },
                "strokeDasharray": "4 3"
              }
            },
            "width": 200,
            "height": 100,
            "zIndex": 10,
            "connector": "smooth",
            "data": {
              "type": "tm.Flow",
              "name": "Páginas",
              "description": "Páginas web leídas desde el disco.",
              "outOfScope": true,
              "reasonOutOfScope": "",
              "hasOpenThreats": false,
              "isBidirectional": false,
              "isEncrypted": false,
              "isPublicNetwork": false,
              "protocol": "",
              "threats": []
            },
            "id": "c4e9aa6e-93d4-4f42-9321-f4882c2c789c",
            "source": {
              "cell": "b7a1e056-cfb8-435e-bc48-8c827cda4885"
            },
            "target": {
              "cell": "b40f6ef8-e1d8-4714-aa98-a0c87e70ba6b"
            },
            "labels": [
              "Páginas"
            ],
            "vertices": [
              {
                "x": 480,
                "y": 460
              }
            ]
          },
          {
            "shape": "flow",
            "attrs": {
              "line": {
                "stroke": "#333333",
                "targetMarker": {
                  "name": "block"
                },
                "sourceMarker": {
                  "name": ""
                },
                "strokeDasharray": "4 3"
              }
            },
            "width": 200,
            "height": 100,
            "zIndex": 10,
            "connector": "smooth",
            "data": {
              "type": "tm.Flow",
              "name": "Lee web \napp config\n",
              "description": "Archivo físico de configuración\nleído desde el disco.",
              "outOfScope": true,
              "reasonOutOfScope": "",
              "hasOpenThreats": false,
              "isBidirectional": false,
              "isEncrypted": false,
              "isPublicNetwork": false,
              "protocol": "",
              "threats": []
            },
            "id": "f2015f32-d688-46ba-bc11-584458867a08",
            "source": {
              "cell": "1e995552-7d00-4052-ade5-2f19ea9946c0"
            },
            "target": {
              "cell": "b40f6ef8-e1d8-4714-aa98-a0c87e70ba6b"
            },
            "labels": [
              "Lee web \napp config\n"
            ],
            "vertices": [
              {
                "x": 587,
                "y": 490
              }
            ]
          },
          {
            "shape": "flow",
            "attrs": {
              "line": {
                "stroke": "#333333",
                "targetMarker": {
                  "name": "block"
                },
                "sourceMarker": {
                  "name": ""
                },
                "strokeDasharray": null
              }
            },
            "width": 200,
            "height": 100,
            "zIndex": 10,
            "connector": "smooth",
            "data": {
              "type": "tm.Flow",
              "name": "Queries",
              "description": "",
              "outOfScope": false,
              "reasonOutOfScope": "",
              "hasOpenThreats": false,
              "isBidirectional": false,
              "isEncrypted": false,
              "isPublicNetwork": false,
              "protocol": "",
              "threats": []
            },
            "id": "b3ab2855-5989-4b9b-9974-4a7a466aed01",
            "source": {
              "cell": "b40f6ef8-e1d8-4714-aa98-a0c87e70ba6b"
            },
            "target": {
              "cell": "5ecc6c28-60bd-428d-8cfb-4287a6dd1e5c"
            },
            "vertices": [
              {
                "x": 760,
                "y": 510
              }
            ],
            "labels": [
              "Queries"
            ]
          },
          {
            "shape": "flow",
            "attrs": {
              "line": {
                "stroke": "#333333",
                "targetMarker": {
                  "name": "block"
                },
                "sourceMarker": {
                  "name": ""
                },
                "strokeDasharray": null
              }
            },
            "width": 200,
            "height": 100,
            "zIndex": 10,
            "connector": "smooth",
            "data": {
              "type": "tm.Flow",
              "name": "Resultados\nWeb App Query",
              "description": "",
              "outOfScope": false,
              "reasonOutOfScope": "",
              "hasOpenThreats": false,
              "isBidirectional": false,
              "isEncrypted": false,
              "isPublicNetwork": false,
              "protocol": "",
              "threats": [
                {
                  "id": "6cac416e-d28c-4f2c-8415-9631d3536cb7",
                  "title": "Ataque Man in the middle",
                  "status": "Mitigated",
                  "severity": "High",
                  "type": "Information disclosure",
                  "description": "Un atacante podría\ninterceptar las\nconsultas de la base\nde datos en tránsito\ny obtener\ninformación\nconfidencial, como\ncredenciales de la\nbase de datos,\nparámetros de\nconsulta o resultados\nde la consulta (es\npoco probable ya\nque el flujo de datos\nse realiza a través de\nuna red privada).",
                  "mitigation": "Aplicar una conexión cifrada\nen el servidor de base de datos.",
                  "modelType": "STRIDE",
                  "new": false,
                  "number": 6,
                  "score": ""
                }
              ]
            },
            "id": "3ac60866-b15f-4db3-a4a0-72efe7f67963",
            "source": {
              "cell": "5ecc6c28-60bd-428d-8cfb-4287a6dd1e5c"
            },
            "target": {
              "cell": "b40f6ef8-e1d8-4714-aa98-a0c87e70ba6b"
            },
            "labels": [
              "Resultados\nWeb App Query"
            ],
            "vertices": [
              {
                "x": 820,
                "y": 385
              }
            ]
          },
          {
            "shape": "trust-boundary-curve",
            "width": 200,
            "height": 100,
            "zIndex": 10,
            "connector": "smooth",
            "data": {
              "type": "tm.Boundary",
              "name": "Límite\nWeb server/Db",
              "description": "",
              "isTrustBoundary": true,
              "hasOpenThreats": false
            },
            "id": "30d3faa4-ebd8-47c9-a742-0723f7e5882f",
            "source": {
              "x": 860,
              "y": 610
            },
            "target": {
              "x": 920,
              "y": 360
            },
            "vertices": [
              {
                "x": 830,
                "y": 470
              }
            ],
            "labels": [
              "Límite\nWeb server/Db"
            ]
          },
          {
            "shape": "flow",
            "attrs": {
              "line": {
                "stroke": "red",
                "strokeWidth": 2.5,
                "targetMarker": {
                  "name": "block"
                },
                "sourceMarker": {
                  "name": ""
                },
                "strokeDasharray": null
              }
            },
            "width": 200,
            "height": 100,
            "zIndex": 10,
            "connector": "smooth",
            "data": {
              "type": "tm.Flow",
              "name": "Web Request\n",
              "description": "Respuestas recibidas por la\naplicación hacia los usuarios.",
              "outOfScope": false,
              "reasonOutOfScope": "",
              "hasOpenThreats": true,
              "isBidirectional": false,
              "isEncrypted": false,
              "isPublicNetwork": false,
              "protocol": "",
              "threats": [
                {
                  "id": "ce73990e-59f2-4634-bbd9-5d7be915da13",
                  "title": "El flujo de datos debe utilizar HTTP/S",
                  "status": "Open",
                  "severity": "High",
                  "type": "Information disclosure",
                  "description": "Estas solicitudes se\ntransmiten a través\nde la Internet\npública y podrían ser\ninterceptadas por un\natacante.",
                  "mitigation": "Las solicitudes deberían\nrequerir HTTPS/S. Esto\nproporcionara confidencialidad\ne integridad. HTTP no debe ser\ncompatible.",
                  "modelType": "STRIDE",
                  "new": false,
                  "number": 2,
                  "score": ""
                }
              ]
            },
            "id": "6676da3f-1291-4273-a424-91e477073005",
            "source": {
              "cell": "32d404da-89de-4432-b650-cd7b55bea9be"
            },
            "target": {
              "cell": "b40f6ef8-e1d8-4714-aa98-a0c87e70ba6b"
            },
            "labels": [
              "Web Request\n"
            ],
            "vertices": [
              {
                "x": 470,
                "y": 200
              },
              {
                "x": 510,
                "y": 240
              },
              {
                "x": 530,
                "y": 270
              }
            ]
          },
          {
            "position": {
              "x": 660,
              "y": 110
            },
            "size": {
              "width": 112.5,
              "height": 60
            },
            "attrs": {
              "text": {
                "text": "Bibliotecario"
              },
              "body": {
                "stroke": "red",
                "strokeWidth": 2.5,
                "strokeDasharray": null
              }
            },
            "visible": true,
            "shape": "actor",
            "id": "f0c66480-aa1a-41fd-9b4f-be06edae62ea",
            "zIndex": 11,
            "data": {
              "type": "tm.Actor",
              "name": "Bibliotecario",
              "description": "(4) Bibliotecario.",
              "outOfScope": false,
              "reasonOutOfScope": "",
              "hasOpenThreats": true,
              "providesAuthentication": false,
              "threats": [
                {
                  "id": "bd06d263-5031-48dc-a3a9-52b4e039cd67",
                  "title": "Suplantación de identidad",
                  "status": "Open",
                  "severity": "Low",
                  "type": "Spoofing",
                  "description": "Acción de amenaza destinada\na acceder y utilizar las\ncredenciales de otro usuario,\ncomo el nombre de usuario y\nla contraseña.",
                  "mitigation": "1. Autenticación\nadecuada\n2. Proteger datos secretos\n3. No almacenar secretos",
                  "modelType": "STRIDE",
                  "new": false,
                  "number": 9,
                  "score": ""
                }
              ]
            }
          },
          {
            "position": {
              "x": 300,
              "y": 520
            },
            "size": {
              "width": 120,
              "height": 60
            },
            "attrs": {
              "text": {
                "text": "Páginas web \nen disco"
              },
              "topLine": {
                "strokeWidth": 1.5,
                "strokeDasharray": null
              },
              "bottomLine": {
                "strokeWidth": 1.5,
                "strokeDasharray": null
              }
            },
            "visible": true,
            "shape": "store",
            "id": "b7a1e056-cfb8-435e-bc48-8c827cda4885",
            "zIndex": 12,
            "data": {
              "type": "tm.Store",
              "name": "Páginas web \nen disco",
              "description": "",
              "outOfScope": false,
              "reasonOutOfScope": "",
              "hasOpenThreats": false,
              "isALog": false,
              "isEncrypted": false,
              "isSigned": false,
              "storesCredentials": false,
              "storesInventory": false,
              "threats": []
            }
          },
          {
            "position": {
              "x": 530,
              "y": 540
            },
            "size": {
              "width": 170,
              "height": 60
            },
            "attrs": {
              "text": {
                "text": "Web Application Config"
              },
              "topLine": {
                "strokeWidth": 1.5,
                "strokeDasharray": null
              },
              "bottomLine": {
                "strokeWidth": 1.5,
                "strokeDasharray": null
              }
            },
            "visible": true,
            "shape": "store",
            "id": "1e995552-7d00-4052-ade5-2f19ea9946c0",
            "zIndex": 13,
            "data": {
              "type": "tm.Store",
              "name": "Web Application Config",
              "description": "",
              "outOfScope": false,
              "reasonOutOfScope": "",
              "hasOpenThreats": false,
              "isALog": false,
              "isEncrypted": false,
              "isSigned": false,
              "storesCredentials": false,
              "storesInventory": false,
              "threats": []
            }
          },
          {
            "position": {
              "x": 900,
              "y": 480
            },
            "size": {
              "width": 120,
              "height": 60
            },
            "attrs": {
              "text": {
                "text": "Base de datos"
              },
              "topLine": {
                "strokeWidth": 1.5,
                "strokeDasharray": null
              },
              "bottomLine": {
                "strokeWidth": 1.5,
                "strokeDasharray": null
              }
            },
            "visible": true,
            "shape": "store",
            "id": "5ecc6c28-60bd-428d-8cfb-4287a6dd1e5c",
            "zIndex": 14,
            "data": {
              "type": "tm.Store",
              "name": "Base de datos",
              "description": "",
              "outOfScope": false,
              "reasonOutOfScope": "",
              "hasOpenThreats": false,
              "isALog": false,
              "isEncrypted": false,
              "isSigned": false,
              "storesCredentials": false,
              "storesInventory": false,
              "threats": []
            }
          }
        ]
      }
    ],
    "diagramTop": 4,
    "reviewer": "Guillermo Vera",
    "threatTop": 9
  }
}